[
  {
    "titulo": "John Wick 4",
    "imagen": "https://image.tmdb.org/t/p/w500/imYg5wZI3phgA0NvZ9rbbsXEGEp.jpg",
    "enlace": "https://tuservidor.com/johnwick4",
    "ranking": 1,
    "badge": "HD"
  },
  {
    "titulo": "Avatar: El camino del agua",
    "imagen": "https://image.tmdb.org/t/p/w500/a4BfxRK8dBgbQqbRxPs8kmLd8LG.jpg",
    "enlace": "https://tuservidor.com/avatar2",
    "ranking": 2,
    "badge": "CINE"
  },
  {
    "titulo": "Spider-Man: No Way Home",
    "imagen": "https://image.tmdb.org/t/p/w500/1g0dhYtq4irTY1GPXvft6k4YLjm.jpg",
    "enlace": "https://tuservidor.com/spiderman",
    "ranking": 3,
    "badge": "4K"
  },
  {
    "titulo": "The Batman",
    "imagen": "https://image.tmdb.org/t/p/w500/74xTEgt7R36Fpooo50r9T25onhq.jpg",
    "enlace": "https://tuservidor.com/batman",
    "ranking": 4,
    "badge": "HD"
  },
  {
    "titulo": "Doctor Strange en el Multiverso",
    "imagen": "https://image.tmdb.org/t/p/w500/9Gtg2DzBhmYamXBS1hKAhiwbBKS.jpg",
    "enlace": "https://tuservidor.com/strange",
    "ranking": 5,
    "badge": "CINE"
  },
  {
    "titulo": "Rápidos y Furiosos 9",
    "imagen": "https://image.tmdb.org/t/p/w500/bOFaAXmWWXC3Rbv4u4uM9ZSzRXP.jpg",
    "enlace": "https://tuservidor.com/rapidos9",
    "ranking": 6,
    "badge": "HD"
  },
  {
    "titulo": "Top Gun: Maverick",
    "imagen": "https://image.tmdb.org/t/p/w500/62HCnUTziyWcpDaBO2i1DX17ljH.jpg",
    "enlace": "https://tuservidor.com/topgun",
    "ranking": 7,
    "badge": "CINE"
  },
  {
    "titulo": "Thor: Love and Thunder",
    "imagen": "https://image.tmdb.org/t/p/w500/pIkRyD18kl4FhoCNQuWxWu5cBLM.jpg",
    "enlace": "https://tuservidor.com/thor4",
    "ranking": 8,
    "badge": "HD"
  },
  {
    "titulo": "Black Panther: Wakanda Forever",
    "imagen": "https://image.tmdb.org/t/p/w500/sv1xJUazXeYqALzczSZ3O6nkH75.jpg",
    "enlace": "https://tuservidor.com/wakanda",
    "ranking": 9,
    "badge": "HD"
  },
  {
    "titulo": "Jurassic World: Dominion",
    "imagen": "https://image.tmdb.org/t/p/w500/kAVRgw7GgK1CfYEJq8ME6EvRIgU.jpg",
    "enlace": "https://tuservidor.com/jurassic",
    "ranking": 10,
    "badge": "CINE"
  }
]
