[
  {
    
    "imagen": "https://image.tmdb.org/t/p/original/yrZqrGVbmoYZJdncnx60JUhzsGm.jpg",
  "enlace": "https://playerinka.blogspot.com/p/lilo-y-stitch.html",
    "ranking": 1,
    "badge": "CINE"
  },
  {
    
    "imagen": "https://image.tmdb.org/t/p/original/5LB5GJzcaEBEb3IhjqnYNsqY5Zs.jpg",
  "enlace": "https://playerinka.blogspot.com/p/karate-kid-leyendas.html",
    "ranking": 2,
    "badge": "CINE"
  },
  {
    
    "imagen": "https://image.tmdb.org/t/p/original/dCJ0OyPQfRvsgP5IvlgT0zoE6bc.jpg",
  "enlace": "https://playerinka.blogspot.com/p/los-diarios-de-la-boticaria-s2-latino.html",
    "ranking": 3,
    "badge": "ANIME"
  },
  {
    
    "imagen": "https://image.tmdb.org/t/p/original/8YdjvU8ehv0nU5jVWuhihu7Adfr.jpg",
  "enlace": "https://playerinka.blogspot.com/p/the-shiunji-family-children-latino.html",
    "ranking": 4,
    "badge": "ANIME"
  },
  {
    
    "imagen": "https://image.tmdb.org/t/p/original/tnHk0MtJeYTJAoPm6dD6EJHKP1k.jpg",
  "enlace": "https://playerinka.blogspot.com/p/enen-no-shouboutai-s3-latino.html",
    "ranking": 5,
    "badge": "ANIME"
  },
  {
    
    "imagen": "https://image.tmdb.org/t/p/original/dkuUbNhVVY8Yvm2pPDfs8AWlxMc.jpg",
  "enlace": "https://playerinka.blogspot.com/p/la-colina-de-las-amapolas.html",
    "ranking": 6,
    "badge": "CINE"
  },
  {
    
    "imagen": "https://image.tmdb.org/t/p/original/eEtkKOa36TYXYiHpNih7BulCgUD.jpg",
  "enlace": "https://playerinka.blogspot.com/p/una-carta-para-momo-momo-e-no-tegami.html",
    "ranking": 7,
    "badge": "ANIME"
  },
  {
    
    "imagen": "https://image.tmdb.org/t/p/original/gaHg0YFyjII0HdkIFDxe5UpA2GY.jpg",
  "enlace": "https://playerinka.blogspot.com/p/alone-in-venice.html",
    "ranking": 8,
    "badge": "HD"
  },
  {
    "imagen": "https://image.tmdb.org/t/p/w500/pIkRyD18kl4FhoCNQuWxWu5cBLM.jpg",
    "enlace": "https://tuservidor.com/wakanda",
    "ranking": 9,
    "badge": "HD"
  },
  {
    
    "imagen": "https://image.tmdb.org/t/p/w500/kAVRgw7GgK1CfYEJq8ME6EvRIgU.jpg",
    "enlace": "https://tuservidor.com/jurassic",
    "ranking": 10,
    "badge": "CINE"
  }
]
