{
  "titulo": "Made in Abyss 1: El amanecer del viaje - (Parte - 1)",
  "sinopsis": "El enigmático Abismo es un lugar implacable y mortal. A pesar de los peligros, todavía captura la imaginación de exploradores como Riko, que desea seguir los pasos de su madre y se entrena para convertirse en un Raider de Cavernas.  Un día, recibe noticias de que su madre murió en el Abismo. Sin embargo, una nota misteriosa le dice a Riko que su madre aún podría estar viva. Con el compromiso de descubrir la verdad sobre el destino de su madre, Riko se embarca en un viaje con un robot robot humanoide llamado Reg. Juntos, descubrirán si tienen lo necesario para sobrevivir donde tantos otros han perecido.",
  "imagen_fondo": "https://image.tmdb.org/t/p/original/lgwoOS8uYQ9iBneUI3ynd5mE9Uj.jpg",
  "poster": "https://image.tmdb.org/t/p/original/acq0pRmtavYypBCoa23rQDOnj4U.jpg",
  "genero": [
    "Animación",
    "Aventura",
    "Misterio",
    "Fantasía",
    "Familia",
    "Ciencia ficción"
  ],
  "servidores": [
    {
      "nombre": "Servidor 1",
      "url": "https://dhcplay.com/e/Ghujtxgy"
    }
  ]
}
